jobsy.py
jobsy-0.1.4.dist-info/METADATA
jobsy-0.1.4.dist-info/WHEEL
jobsy-0.1.4.dist-info/RECORD
