Metadata-Version: 2.3
Name: jobsy
Version: 0.1.4
Summary: 
Author: renan_moretto@outlook.com
Requires-Python: >=3.9
Classifier: Programming Language :: Python :: 3
Classifier: Programming Language :: Python :: 3.9
Classifier: Programming Language :: Python :: 3.10
Classifier: Programming Language :: Python :: 3.11
Classifier: Programming Language :: Python :: 3.12
Classifier: Programming Language :: Python :: 3.13
Requires-Dist: pytz (>=2025.2,<2026.0)
Project-URL: Repository, https://github.com/renanmoretto/jobsy
